tc_db_base/__init__.py
tc_db_base/client.py
tc_db_base/pubsub.py
tc_db_base/query_builder.py
tc_db_base/repository.py
tc_db_base/server.py
tc_db_base/service.py
tc_db_base/setup.py
tc_db_base/transaction.py
tc_db_base/examples/basic_usage.py
tc_db_base/schema/__init__.py
tc_db_base/schema/validator.py
tc_db_base/tc_db_base/__init__.py
tc_db_base/tc_db_base/client.py
tc_db_base/tc_db_base/repository.py
tc_db_base/tc_db_base/server.py
tc_db_base/tc_db_base/service.py
tc_db_base/tc_db_base/schema/__init__.py
tc_db_base/tc_db_base/schema/validator.py
tc_db_base/tests/__init__.py
tc_db_base/tests/conftest.py
tc_db_base-1.0.3.dist-info/licenses/LICENSE
tc_db_base-1.0.3.dist-info/METADATA
tc_db_base-1.0.3.dist-info/WHEEL
tc_db_base-1.0.3.dist-info/entry_points.txt
tc_db_base-1.0.3.dist-info/top_level.txt
tc_db_base-1.0.3.dist-info/RECORD
