Metadata-Version: 2.4
Name: tc-db-base
Version: 1.0.3
Summary: Schema-driven MongoDB database module with auto-generated repositories
Home-page: https://github.com/task-circuit/tc-db-base
Author: Yashvanth D
Author-email: Yashvanth D <dev@taskcircuit.com>
License: MIT
Project-URL: Homepage, https://github.com/task-circuit/tc-db-base
Project-URL: Documentation, https://github.com/task-circuit/tc-db-base#readme
Project-URL: Repository, https://github.com/task-circuit/tc-db-base
Project-URL: Bug Tracker, https://github.com/task-circuit/tc-db-base/issues
Keywords: mongodb,database,schema,repository,orm,task-circuit
Classifier: Development Status :: 4 - Beta
Classifier: Intended Audience :: Developers
Classifier: License :: OSI Approved :: MIT License
Classifier: Operating System :: OS Independent
Classifier: Programming Language :: Python :: 3
Classifier: Programming Language :: Python :: 3.8
Classifier: Programming Language :: Python :: 3.9
Classifier: Programming Language :: Python :: 3.10
Classifier: Programming Language :: Python :: 3.11
Classifier: Programming Language :: Python :: 3.12
Classifier: Topic :: Database
Classifier: Topic :: Software Development :: Libraries :: Python Modules
Requires-Python: >=3.8
License-File: LICENSE
Requires-Dist: pymongo>=4.0.0
Provides-Extra: dev
Requires-Dist: pytest>=7.0.0; extra == "dev"
Requires-Dist: pytest-cov>=4.0.0; extra == "dev"
Requires-Dist: black>=23.0.0; extra == "dev"
Requires-Dist: flake8>=6.0.0; extra == "dev"
Requires-Dist: mypy>=1.0.0; extra == "dev"
Provides-Extra: flask
Requires-Dist: flask>=2.0.0; extra == "flask"
Requires-Dist: flask-cors>=4.0.0; extra == "flask"
Dynamic: author
Dynamic: home-page
Dynamic: license-file
Dynamic: requires-python
